enosapi/__init__.py
enosapi/client/EnOSDefaultClient.py
enosapi/client/__init__.py
enosapi/request/ApplyCertificateByDeviceKeyRequest.py
enosapi/request/CreateProductRequest.py
enosapi/request/EnOSRequest.py
enosapi/request/ListProductsRequest.py
enosapi/request/PostMeasurepointsEnOSRequest.py
enosapi/request/__init__.py
enosapi/response/EnOSResponse.py
enosapi/response/__init__.py
enosapi/sample/SimplePostMeasurePoint.py
enosapi/sample/__init__.py
enosapi/util/Sign.py
enosapi/util/__init__.py
enosapi/util/const.py
enos_api_sdk_python-0.0.4.dist-info/METADATA
enos_api_sdk_python-0.0.4.dist-info/WHEEL
enos_api_sdk_python-0.0.4.dist-info/top_level.txt
enos_api_sdk_python-0.0.4.dist-info/RECORD
