Metadata-Version: 2.1
Name: enos-api-sdk-python
Version: 0.0.4
Summary: EnOS API SDK for Python
Home-page: https://github.com/EnvisionIot/enos-api-sdk-python.git
Author: lihu.yang
Author-email: lihu.yang@envision-digital.com
License: UNKNOWN
Platform: UNKNOWN
Classifier: Programming Language :: Python :: 2.7
Classifier: Programming Language :: Python :: 3.5
Classifier: Programming Language :: Python :: 3.6
Requires-Dist: pyOpenSSL (==18.0.0)
Requires-Dist: requests (==2.12.4)
